{"name":"Codeaholics","tagline":"*the* Hong Kong Programming Group","body":"### Codeaholics\r\n\r\nWe are a group of programmers from Hong Kong.\r\nWe meet up once a month to have a few talks, and chat.\r\n\r\n### Join the Mailing List\r\n\r\nEvery day we are talking about the latest developments on the Web and Mobile.\r\nJoin us at [the Codeaholics Google Group](http://groups.google.com/group/codeaholics)!\r\n\r\n### Facebook\r\n\r\nWe're also on facebook.\r\nCome like [the Codeaholics Facebook page](https://www.facebook.com/codeaholics)\r\n\r\n### Twitter\r\n\r\nFollow [@Codeaholics](https://twitter.com/codeaholics) on Twitter for the latest news.","google":"","note":"Don't delete this file! It's used internally to help with page regeneration."}